{
    "data": {
        "attributes": {
            "type": "object",
            "properties": {
                "permissions": {
                    "type": "object",
                    "patternProperties": {
                        "^\\w+\\-w*\\-\\w+$": {
                            "enum": [
                                "READ",
                                "WRITE",
                                "CREATE",
                                "UPDATE",
                                "DELETE",
                                "ADMIN"
                            ]
                        }
                    }
                }
            }
        },
        "required": [
            "attributes"
        ],
        "additionalProperties": false
    },
    "required": [
        "data"
    ],
    "additionalProperties": false
}